pytmcstepper-0.21.1.dist-info/licenses/LICENSE
tmc_driver/__init__.py
tmc_driver/_tmc_exceptions.py
tmc_driver/_tmc_math.py
tmc_driver/_tmc_stallguard.py
tmc_driver/_tmc_stepperdriver.py
tmc_driver/_tmc_validation.py
tmc_driver/_tmc_xxxx.py
tmc_driver/platform_utils.py
tmc_driver/tmc_2208.py
tmc_driver/tmc_2209.py
tmc_driver/tmc_220x.py
tmc_driver/tmc_2240.py
tmc_driver/tmc_5160.py
tmc_driver/com/__init__.py
tmc_driver/com/_tmc_com.py
tmc_driver/com/_tmc_com_spi.py
tmc_driver/com/_tmc_com_spi_base.py
tmc_driver/com/_tmc_com_spi_circuitpython.py
tmc_driver/com/_tmc_com_spi_ftdi.py
tmc_driver/com/_tmc_com_spi_micropython.py
tmc_driver/com/_tmc_com_uart.py
tmc_driver/com/_tmc_com_uart_base.py
tmc_driver/com/_tmc_com_uart_circuitpython.py
tmc_driver/com/_tmc_com_uart_micropython.py
tmc_driver/enable_control/__init__.py
tmc_driver/enable_control/_tmc_ec.py
tmc_driver/enable_control/_tmc_ec_pin.py
tmc_driver/enable_control/_tmc_ec_toff.py
tmc_driver/motion_control/__init__.py
tmc_driver/motion_control/_tmc_mc.py
tmc_driver/motion_control/_tmc_mc_int_ramp_generator.py
tmc_driver/motion_control/_tmc_mc_step_dir.py
tmc_driver/motion_control/_tmc_mc_step_pio.py
tmc_driver/motion_control/_tmc_mc_step_pio_base.py
tmc_driver/motion_control/_tmc_mc_step_pio_circuitpython.py
tmc_driver/motion_control/_tmc_mc_step_pio_micropython.py
tmc_driver/motion_control/_tmc_mc_step_pwm_dir.py
tmc_driver/motion_control/_tmc_mc_step_reg.py
tmc_driver/motion_control/_tmc_mc_vactual.py
tmc_driver/reg/__init__.py
tmc_driver/reg/_tmc2209_reg.py
tmc_driver/reg/_tmc220x_reg.py
tmc_driver/reg/_tmc224x_reg.py
tmc_driver/reg/_tmc5160_reg.py
tmc_driver/reg/_tmc_reg.py
tmc_driver/reg/_tmc_shared_regs.py
tmc_driver/tmc_gpio/__init__.py
tmc_driver/tmc_gpio/_tmc_gpio_board_base.py
tmc_driver/tmc_gpio/_tmc_gpio_board_circuitpython.py
tmc_driver/tmc_gpio/_tmc_gpio_board_ftdi.py
tmc_driver/tmc_gpio/_tmc_gpio_board_gpiozero.py
tmc_driver/tmc_gpio/_tmc_gpio_board_micropython.py
tmc_driver/tmc_gpio/_tmc_gpio_board_periphery.py
pytmcstepper-0.21.1.dist-info/METADATA
pytmcstepper-0.21.1.dist-info/WHEEL
pytmcstepper-0.21.1.dist-info/top_level.txt
pytmcstepper-0.21.1.dist-info/RECORD
