Metadata-Version: 2.4
Name: PyTmcStepper
Version: 0.21.1
Summary: This is a Python libary to drive a stepper motor with a Trinamic stepper driver and a single board computer like a Raspberry Pi
Author-email: Christian Köhlke <christian@koehlke.de>
License-Expression: GPL-3.0
Project-URL: Homepage, https://github.com/Chr157i4n/PyTmcStepper
Project-URL: Bug Tracker, https://github.com/Chr157i4n/PyTmcStepper/issues
Classifier: Programming Language :: Python :: 3
Classifier: Programming Language :: Python :: Implementation :: CPython
Classifier: Programming Language :: Python :: Implementation :: MicroPython
Classifier: Operating System :: POSIX :: Linux
Classifier: Development Status :: 4 - Beta
Classifier: Intended Audience :: Developers
Classifier: Natural Language :: English
Classifier: Topic :: System :: Hardware :: Hardware Drivers
Requires-Python: >=3.10
License-File: LICENSE
Provides-Extra: uart
Requires-Dist: pyserial; extra == "uart"
Provides-Extra: spi
Requires-Dist: spidev; extra == "spi"
Provides-Extra: ftdi
Requires-Dist: pyftdi; extra == "ftdi"
Provides-Extra: raspberry-pi
Requires-Dist: RPi.GPIO; extra == "raspberry-pi"
Provides-Extra: raspberry-pi5
Requires-Dist: gpiozero; extra == "raspberry-pi5"
Provides-Extra: nvidia-jetson
Requires-Dist: Jetson.GPIO; extra == "nvidia-jetson"
Provides-Extra: luckfox-pico
Requires-Dist: python-periphery; extra == "luckfox-pico"
Provides-Extra: orange-pi
Requires-Dist: OPi.GPIO; extra == "orange-pi"
Dynamic: license-file
